SiEPICLabTestParam/ElectroOpticDevice.py
SiEPICLabTestParam/TestParameters.py
SiEPICLabTestParam/__init__.py
SiEPICLabTestParam/__main__.py
SiEPICLabTestParam/autoMeasure.py
SiEPICLabTestParam/autoMeasurePanel.py
SiEPICLabTestParam/autoMeasureProgressDialog.py
SiEPICLabTestParam/cli.py
SiEPICLabTestParam/filterFrame.py
SiEPICLabTestParam/informationframes.py
SiEPICLabTestParam/logWriter.py
SiEPICLabTestParam/measurementRoutines.py
SiEPICLabTestParam/outputlogPanel.py
SiEPICLab-0.0.5.dist-info/LICENSE
SiEPICLab-0.0.5.dist-info/METADATA
SiEPICLab-0.0.5.dist-info/WHEEL
SiEPICLab-0.0.5.dist-info/top_level.txt
SiEPICLab-0.0.5.dist-info/RECORD
