Metadata-Version: 2.1
Name: SiEPICLab
Version: 0.0.5
Summary: Create Testing routine files for use with the SiEPICLAB testing package
Home-page: https://github.com/SiEPIC/pyOptomip
Author: Jon Barnes and Madeline Mahanloo
Author-email: jonathanyorkbarnes@gmail.com
License: UNKNOWN
Platform: UNKNOWN
Classifier: Programming Language :: Python :: 3
Classifier: License :: OSI Approved :: MIT License
Classifier: Operating System :: OS Independent
Requires-Python: >=3.7
License-File: LICENSE
Requires-Dist: wxPython
Requires-Dist: PyYAML
Requires-Dist: matplotlib
Requires-Dist: numpy
Requires-Dist: scipy
Requires-Dist: attrdict
